ramose.py
ramose-1.0.8.dist-info/LICENSE
ramose-1.0.8.dist-info/METADATA
ramose-1.0.8.dist-info/WHEEL
ramose-1.0.8.dist-info/RECORD
